README.rst
setup.py
opendna/__init__.py
opendna/common/__init__.py
opendna/common/_version.py
opendna/common/decorators.py
opn_oss_py_common.egg-info/PKG-INFO
opn_oss_py_common.egg-info/SOURCES.txt
opn_oss_py_common.egg-info/dependency_links.txt
opn_oss_py_common.egg-info/entry_points.txt
opn_oss_py_common.egg-info/requires.txt
opn_oss_py_common.egg-info/top_level.txt